leppard/__init__.py
leppard-0.1.0.dist-info/LICENSE.md
leppard-0.1.0.dist-info/WHEEL
leppard-0.1.0.dist-info/METADATA
leppard-0.1.0.dist-info/RECORD
