Metadata-Version: 2.1
Name: leppard
Version: 0.1.0
Summary: Pour some sugar on the cli
Home-page: https://github.com/harrisonpim/leppard
License: UNKNOWN
Author: Harrison Pim
Classifier: License :: OSI Approved :: MIT License
Requires-Dist: black==19.10b0 ; extra == "dev"
Requires-Dist: flake8==3.8.1 ; extra == "dev"
Requires-Dist: isort==4.3.21 ; extra == "dev"
Provides-Extra: dev
